[    {
        "automatic": true,
        "deliveredUnits": 0,
        "endDate": 1714514394.5547218,
        "endDateReadable": "2024-04-30 14:59:54.554722",
        "insulinType": 1,
        "isMutable": false,
        "manuallyEntered": false,
        "startDate": 1714514094.0966082,
        "startDateReadable": "2024-04-30 14:54:54.096608",
        "syncIdentifier": "74656d70426173616c20302e323520323032342d30342d33305432313a35343a35345a",
        "type": "tempBasal",
        "unit": "U/hour",
        "value": 0.5,
        "wasProgrammedByPumpUI": false
    },
    {
        "automatic": true,
        "deliveredUnits": 0,
        "endDate": 1714514696.143707,
        "endDateReadable": "2024-04-30 15:04:56.143707",
        "insulinType": 1,
        "isMutable": false,
        "manuallyEntered": false,
        "startDate": 1714514394.55824,
        "startDateReadable": "2024-04-30 14:59:54.558240",
        "syncIdentifier": "74656d70426173616c20302e31373520323032342d30342d33305432313a35393a35345a",
        "type": "tempBasal",
        "unit": "U/hour",
        "value": 0.35,
        "wasProgrammedByPumpUI": false
    },
    {
        "automatic": true,
        "deliveredUnits": 0.05,
        "endDate": 1714514997.494992,
        "endDateReadable": "2024-04-30 15:09:57.494992",
        "insulinType": 1,
        "isMutable": false,
        "manuallyEntered": false,
        "startDate": 1714514696.148495,
        "startDateReadable": "2024-04-30 15:04:56.148495",
        "syncIdentifier": "74656d70426173616c20302e3320323032342d30342d33305432323a30343a35365a",
        "type": "tempBasal",
        "unit": "U/hour",
        "value": 0.6,
        "wasProgrammedByPumpUI": false
    },
    {
        "automatic": true,
        "deliveredUnits": 0.05,
        "endDate": 1714515494.095961,
        "endDateReadable": "2024-04-30 15:18:14.095961",
        "insulinType": 1,
        "isMutable": false,
        "manuallyEntered": false,
        "startDate": 1714514997.4994202,
        "startDateReadable": "2024-04-30 15:09:57.499420",
        "syncIdentifier": "74656d70426173616c20302e3320323032342d30342d33305432323a30393a35375a",
        "type": "tempBasal",
        "unit": "U/hour",
        "value": 0.6,
        "wasProgrammedByPumpUI": false
    },
    {
        "automatic": true,
        "deliveredUnits": 0,
        "endDate": 1714515595.164248,
        "endDateReadable": "2024-04-30 15:19:55.164248",
        "insulinType": 1,
        "isMutable": false,
        "manuallyEntered": false,
        "startDate": 1714515494.099016,
        "startDateReadable": "2024-04-30 15:18:14.099016",
        "syncIdentifier": "74656d70426173616c20302e3120323032342d30342d33305432323a31383a31345a",
        "type": "tempBasal",
        "unit": "U/hour",
        "value": 0.2,
        "wasProgrammedByPumpUI": false
    },
    {
        "automatic": true,
        "deliveredUnits": 0,
        "endDate": 1714515901.883185,
        "endDateReadable": "2024-04-30 15:25:01.883185",
        "insulinType": 1,
        "isMutable": false,
        "manuallyEntered": false,
        "startDate": 1714515595.167608,
        "startDateReadable": "2024-04-30 15:19:55.167608",
        "syncIdentifier": "74656d70426173616c20302e313520323032342d30342d33305432323a31393a35355a",
        "type": "tempBasal",
        "unit": "U/hour",
        "value": 0.3,
        "wasProgrammedByPumpUI": false
    },
    {
        "automatic": true,
        "deliveredUnits": 0,
        "endDate": 1714516192.9595819,
        "endDateReadable": "2024-04-30 15:29:52.959582",
        "insulinType": 1,
        "isMutable": false,
        "manuallyEntered": false,
        "startDate": 1714515901.886461,
        "startDateReadable": "2024-04-30 15:25:01.886461",
        "syncIdentifier": "74656d70426173616c20302e303520323032342d30342d33305432323a32353a30315a",
        "type": "tempBasal",
        "unit": "U/hour",
        "value": 0.1,
        "wasProgrammedByPumpUI": false
    },
    {
        "automatic": true,
        "deliveredUnits": 0,
        "endDate": 1714516498.3596501,
        "endDateReadable": "2024-04-30 15:34:58.359650",
        "insulinType": 1,
        "isMutable": false,
        "manuallyEntered": false,
        "startDate": 1714516192.963063,
        "startDateReadable": "2024-04-30 15:29:52.963063",
        "syncIdentifier": "74656d70426173616c20302e313520323032342d30342d33305432323a32393a35325a",
        "type": "tempBasal",
        "unit": "U/hour",
        "value": 0.3,
        "wasProgrammedByPumpUI": false
    },
    {
        "automatic": true,
        "deliveredUnits": 0,
        "endDate": 1714516798.134145,
        "endDateReadable": "2024-04-30 15:39:58.134145",
        "insulinType": 1,
        "isMutable": false,
        "manuallyEntered": false,
        "startDate": 1714516498.362757,
        "startDateReadable": "2024-04-30 15:34:58.362757",
        "syncIdentifier": "74656d70426173616c20302e3220323032342d30342d33305432323a33343a35385a",
        "type": "tempBasal",
        "unit": "U/hour",
        "value": 0.4,
        "wasProgrammedByPumpUI": false
    },
    {
        "automatic": true,
        "deliveredUnits": 0,
        "endDate": 1714517101.643962,
        "endDateReadable": "2024-04-30 15:45:01.643962",
        "insulinType": 1,
        "isMutable": false,
        "manuallyEntered": false,
        "startDate": 1714516798.1373482,
        "startDateReadable": "2024-04-30 15:39:58.137348",
        "syncIdentifier": "74656d70426173616c20302e3020323032342d30342d33305432323a33393a35385a",
        "type": "tempBasal",
        "unit": "U/hour",
        "value": 0,
        "wasProgrammedByPumpUI": false
    },
    {
        "automatic": true,
        "deliveredUnits": 0.05,
        "endDate": 1714516801.378821,
        "endDateReadable": "2024-04-30 15:40:01.378821",
        "insulinType": 1,
        "isMutable": false,
        "manuallyEntered": false,
        "startDate": 1714516799.378821,
        "startDateReadable": "2024-04-30 15:39:59.378821",
        "syncIdentifier": "626f6c757320302e303520323032342d30342d33305432323a33393a35395a",
        "type": "bolus",
        "unit": "U",
        "value": 0.05,
        "wasProgrammedByPumpUI": false
    },
    {
        "automatic": true,
        "deliveredUnits": 0,
        "endDate": 1714517396.961866,
        "endDateReadable": "2024-04-30 15:49:56.961866",
        "insulinType": 1,
        "isMutable": false,
        "manuallyEntered": false,
        "startDate": 1714517101.647306,
        "startDateReadable": "2024-04-30 15:45:01.647306",
        "syncIdentifier": "74656d70426173616c20302e3020323032342d30342d33305432323a34353a30315a",
        "type": "tempBasal",
        "unit": "U/hour",
        "value": 0,
        "wasProgrammedByPumpUI": false
    },
    {
        "automatic": true,
        "deliveredUnits": 0.05,
        "endDate": 1714517104.753222,
        "endDateReadable": "2024-04-30 15:45:04.753222",
        "insulinType": 1,
        "isMutable": false,
        "manuallyEntered": false,
        "startDate": 1714517102.753222,
        "startDateReadable": "2024-04-30 15:45:02.753222",
        "syncIdentifier": "626f6c757320302e303520323032342d30342d33305432323a34353a30325a",
        "type": "bolus",
        "unit": "U",
        "value": 0.05,
        "wasProgrammedByPumpUI": false
    },
    {
        "automatic": true,
        "deliveredUnits": 0,
        "endDate": 1714517699.9631891,
        "endDateReadable": "2024-04-30 15:54:59.963189",
        "insulinType": 1,
        "isMutable": false,
        "manuallyEntered": false,
        "startDate": 1714517396.963424,
        "startDateReadable": "2024-04-30 15:49:56.963424",
        "syncIdentifier": "74656d70426173616c20302e3220323032342d30342d33305432323a34393a35365a",
        "type": "tempBasal",
        "unit": "U/hour",
        "value": 0.4,
        "wasProgrammedByPumpUI": false
    },
    {
        "automatic": true,
        "deliveredUnits": 0,
        "endDate": 1714517892.726407,
        "endDateReadable": "2024-04-30 15:58:12.726407",
        "insulinType": 1,
        "isMutable": false,
        "manuallyEntered": false,
        "startDate": 1714517699.9665809,
        "startDateReadable": "2024-04-30 15:54:59.966581",
        "syncIdentifier": "74656d70426173616c20302e3220323032342d30342d33305432323a35343a35395a",
        "type": "tempBasal",
        "unit": "U/hour",
        "value": 0.4,
        "wasProgrammedByPumpUI": false
    },
    {
        "endDate": 1714517892.726407,
        "endDateReadable": "2024-04-30 15:58:12.726407",
        "isMutable": false,
        "manuallyEntered": false,
        "startDate": 1714517892.726407,
        "startDateReadable": "2024-04-30 15:58:12.726407",
        "syncIdentifier": "73757370656e6420302e3020323032342d30342d33305432323a35383a31325a",
        "type": "suspend",
        "unit": "U",
        "value": 0,
        "wasProgrammedByPumpUI": false
    },
    {
        "endDate": 1714531049.1750169,
        "endDateReadable": "2024-04-30 19:37:29.175017",
        "insulinType": 1,
        "isMutable": false,
        "manuallyEntered": false,
        "startDate": 1714531049.1750169,
        "startDateReadable": "2024-04-30 19:37:29.175017",
        "syncIdentifier": "726573756d6520302e3020323032342d30352d30315430323a33373a32395a",
        "type": "resume",
        "unit": "U",
        "value": 0,
        "wasProgrammedByPumpUI": false
    },
    {
        "automatic": true,
        "deliveredUnits": 0,
        "endDate": 1714531493.19128,
        "endDateReadable": "2024-04-30 19:44:53.191280",
        "insulinType": 1,
        "isMutable": false,
        "manuallyEntered": false,
        "startDate": 1714531064.591965,
        "startDateReadable": "2024-04-30 19:37:44.591965",
        "syncIdentifier": "74656d70426173616c20302e3020323032342d30352d30315430323a33373a34345a",
        "type": "tempBasal",
        "unit": "U/hour",
        "value": 0,
        "wasProgrammedByPumpUI": false
    },
    {
        "automatic": false,
        "deliveredUnits": 3.5,
        "endDate": 1714531282.849591,
        "endDateReadable": "2024-04-30 19:41:22.849591",
        "insulinType": 1,
        "isMutable": false,
        "manuallyEntered": false,
        "startDate": 1714531142.849591,
        "startDateReadable": "2024-04-30 19:39:02.849591",
        "syncIdentifier": "626f6c757320332e3520323032342d30352d30315430323a33393a30325a",
        "type": "bolus",
        "unit": "U",
        "value": 3.5,
        "wasProgrammedByPumpUI": false
    }
]
